golf_auth/__init__.py
golf_auth/crypto.py
golf_auth/provider.py
golf_auth/sdk.py
golf_auth-0.1.0.dist-info/METADATA
golf_auth-0.1.0.dist-info/WHEEL
golf_auth-0.1.0.dist-info/top_level.txt
golf_auth-0.1.0.dist-info/RECORD
