Metadata-Version: 2.4
Name: golf_auth
Version: 0.1.0
Summary: Golf Auth - Secure OAuth token storage and management for MCP servers.
Author-email: Antoni Gmitruk <antoni@golf.dev>
License: MIT
Project-URL: Homepage, https://golf.dev
Keywords: oauth,tokens,security,encryption,mcp
Classifier: Development Status :: 4 - Beta
Classifier: License :: OSI Approved :: MIT License
Classifier: Programming Language :: Python :: 3
Classifier: Programming Language :: Python :: 3.8
Classifier: Programming Language :: Python :: 3.9
Classifier: Programming Language :: Python :: 3.10
Classifier: Programming Language :: Python :: 3.11
Classifier: Topic :: Software Development :: Libraries :: Python Modules
Classifier: Topic :: Security
Requires-Python: >=3.8
Requires-Dist: fastapi>=0.104.0
Requires-Dist: uvicorn>=0.24.0
Requires-Dist: httpx>=0.25.0
Requires-Dist: pydantic>=2.4.2
Requires-Dist: click>=8.1.7
Requires-Dist: python-dotenv>=1.0.0
Requires-Dist: starlette>=0.31.1
Requires-Dist: cryptography>=42.0.0
Provides-Extra: dev
Requires-Dist: pytest>=6.0; extra == "dev"
Requires-Dist: black>=23.0.0; extra == "dev"
Requires-Dist: isort>=5.10.0; extra == "dev"
